{
    "Storelab": [
        "https://storelab-rc.ru/",
        "https://storelab-rc.ru/contacts.htm"
    ],
    "DataRC": [
        "http://www.datarc.ru/",
        "https://www.datarc.ru/contacts/"
    ],
    "Честная Медицина": [
        "https://secondopinions.ru/"
    ],
    "Direkt": [
        "https://direkt.ink/",
        "https://direkt.ink/contacts/"
    ],
    "Логистика. Бизнес. Решения": [
        "https://leagile.ru/",
        "https://leagile.ru/#contacts"
    ],
    "Инженерно-техническая фирма": [
        "https://itfirm.ru/pr-n-12--vesy?erid=Y1jgkD79Vt9MFk5WJoMcGkZJzPgJ",
        "https://itfirm.ru/vakansii"
    ],
    "1С центр автоматизации": [
        "https://65555.ru/"
    ],
    "Дока IT": [
        "http://doka-it.ru/",
        "http://doka-it.ru/company/vacancy/",
        "http://doka-it.ru/contacts/"
    ],
    "Айтекс": [
        "https://itex.ru/",
        "https://itex.ru/company/vacancy/"
    ],
    "Datarc": [
        "https://www.datarc.ru/",
        "https://www.datarc.ru/contacts/"
    ],
    "Арсис": [
        "https://www.arsis.ru/",
        "https://www.arsis.ru/contacts"
    ],
    "Яндекс": [
        "https://yandex.ru/maps/4/belgorod/house/Z08YcwFnTkIDQFtqfXpxcXlqYA==/"
    ],
    "Сбер офис": [
        "http://www.sberbank.ru/"
    ],
    "Ланит": [
        "http://www.lanit.ru/",
        "https://job.lanit.ru",
        "http://www.lanit.ru/contact/"
    ],
    "Авито": [
        "https://www.avito.ru/"
    ],
    "VK": [
        "https://vk.company/",
        "https://team.vk.company/vacancy/",
        "https://team.vk.company/",
        "https://vk.company/ru/company/contacts/"
    ],
    "Контур": [
        "https://kontur.ru/"
    ],
    "Лаборатория Касперского": [
        "https://www.kaspersky.ru/",
        "https://careers.kaspersky.ru/"
    ],
    "Завод вычислительной техники ICL Техно": [
        "http://www.icl-techno.ru/",
        "http://www.icl-techno.ru/contacts/"
    ],
    "Yadro": [
        "https://yadro.com/",
        "https://careers.yadro.com"
    ],
    "Сбербанк Технологии": [
        "https://sbertech.ru/",
        "https://rabota.sber.ru/search?company=%D0%90%D0%9E+%D0%A1%D0%B1%D0%B5%D1%80%D0%B1%D0%B0%D0%BD%D0%BA-%D0%A2%D0%B5%D1%85%D0%BD%D0%BE%D0%BB%D0%BE%D0%B3%D0%B8%D0%B8",
        "https://sbertech.ru/contacts"
    ],
    "Медиалогия": [
        "https://www.mlg.ru/",
        "https://www.mlg.ru/about/vacancy/",
        "https://www.mlg.ru/contacts/"
    ],
    "Центр финансовых технологий": [
        "https://www.cft.ru/",
        "https://team.cft.ru/",
        "https://www.cft.ru/contacts"
    ],
    "СКБ Контур": [
        "https://kontur.ru/"
    ],
    "Центр программистов BePro": [
        "https://bepro.uz/"
    ],
    "Aiva Group": [
        "http://aiva.group/"
    ],
    "Astana Hub С3.5": [
        "https://astanahub.com/"
    ],
    "Манимен": [
        "https://moneyman.ru/",
        "https://moneyman.ru/vacancy/",
        "https://moneyman.ru/contacts/"
    ],
    "Sharifa com": [
        "http://sharifa.uz/"
    ],
    "Сигнатек": [
        "https://www.signatec.ru/",
        "https://www.signatec.ru/vacancy"
    ],
    "DataLine": [
        "https://www.dtln.ru/",
        "https://www.dtln.ru/kompaniya/vakansii",
        "https://www.dtln.ru/kontakty"
    ],
    "Турвизор": [
        "http://tourvisor.ru/"
    ],
    "LeverX Group": [
        "https://leverx.com/"
    ],
    "Системы Папилон": [
        "http://www.papillon.ru/",
        "http://www.papillon.ru/kontakty-i-rekvizity/"
    ],
    "ISsoft": [
        "https://issoft.by/",
        "https://issoft.by/vacancies/",
        "https://issoft.by/contacts/"
    ],
    "PS Cloud Services": [
        "https://yandex.ru/maps/org/mybuh_kz/114462401295/"
    ],
    "СимбирСофт": [
        "https://yandex.ru/maps/org/koder_ul/1132527920/"
    ],
    "ТерраЛинк": [
        "https://terralink.ru/",
        "https://terralink.ru/career/",
        "https://terralink.ru/about/contacts/"
    ],
    "Инфосистемы Джет": [
        "https://jet.su/?utm_content=Jetmoskow&utm_medium=organic&utm_source=yasprav",
        "https://jet.su/career/vacancies/",
        "https://jet.su/career/",
        "https://jet.su/about/contacts/"
    ],
    "Rnt Group": [
        "https://www.rntgroup.com/",
        "https://www.rntgroup.com/career/",
        "https://www.rntgroup.com/contact-us/"
    ],
    "Ай-Теко": [
        "https://www.i-teco.ru/"
    ],
    "Huawei": [
        "https://www.huawei.com/uz/",
        "https://www.huawei.com/uz/contact-us"
    ],
    "Компьютеры и Сети": [
        "https://vc-lan.ru/",
        "https://vc-lan.ru/career",
        "https://vc-lan.ru/contacts"
    ],
    "ТК Полёт": [
        "https://poleteam.ru/",
        "https://hh.ru/employer/3283506",
        "https://poleteam.ru/#contacts"
    ],
    "ФТО": [
        "http://fto.com.ru/",
        "http://fto.com.ru/jobs/",
        "https://fto.com.ru/career/",
        "http://fto.com.ru/contacts/"
    ],
    "Fort Dialogue": [
        "http://www.fortdialog.ru/",
        "/company/career.php",
        "http://www.fortdialog.ru/filials/"
    ],
    "Semrush": [
        "http://careers.semrush.com/"
    ],
    "Консоль": [
        "https://console.su/"
    ],
    "Циан": [
        "https://spb.cian.ru/"
    ],
    "Центр высоких технологий": [
        "http://www.htc-cs.ru/",
        "http://www.htc-cs.ru/about/about-us/contacts"
    ],
    "Itransition": [
        "https://itransition.by/",
        "https://itransition.by/careers/vacancies"
    ],
    "Селектел": [
        "https://selectel.ru/",
        "https://selectel.ru/careers/all/",
        "https://selectel.ru/about/contacts/"
    ],
    "Регула": [
        "https://regulaforensics.com/"
    ],
    "Консист-ос": [
        "https://consyst-os.ru/",
        "https://rosatom-career.ru/",
        "https://consyst-os.ru/career",
        "https://consyst-os.ru/contacts"
    ],
    "Центр обработки данных": [
        "https://yandex.ru/maps/213/moscow/house/Z04Ycw5nSEwOQFtvfXtydn1jZQ==/"
    ],
    "1С Гигабайт": [
        "https://gigansk.ru/",
        "https://gigansk.ru/vacancies/",
        "https://gigansk.ru/kontakty/"
    ],
    "Гэндальф": [
        "https://gendalf.ru/",
        "https://gendalf.ru/career/"
    ],
    "Норникель Спутник": [
        "https://sputnik.nornik.ru/",
        "https://sputnik.nornik.ru/career/",
        "https://sputnik.nornik.ru/contacts/"
    ],
    "Intact": [
        "http://www.intact.ru/",
        "http://www.intact.ru/ru/about/career",
        "http://www.intact.ru/ru/contacts"
    ],
    "Синимекс": [
        "https://www.cinimex.ru/"
    ],
    "1С Первый Бит": [
        "https://kaliningrad.1cbit.ru/",
        "https://kaliningrad.1cbit.ru/contacts/"
    ],
    "Align Technology": [
        "http://aligntech.com/"
    ],
    "СКБ Лаб": [
        "http://skblab.ru/"
    ],
    "Легион": [
        "https://sozdanie-saytove.ru/",
        "https://sozdanie-saytove.ru/kontakt/"
    ],
    "Open Service": [
        "https://open-s.info/",
        "https://open-s.info/company/vacancies/",
        "https://open-s.info/contacts/"
    ],
    "ICL Services": [
        "https://yandex.ru/maps/org/pedant_ru/85756074472/"
    ],
    "Майндбокс": [
        "https://mindbox.ru/",
        "https://mindbox.ru/contacts/"
    ],
    "Уральская консалтинговая компания": [
        "http://u-kk.ru/"
    ],
    "Опен Сервис": [
        "https://open-s.info/",
        "https://open-s.info/company/vacancies/",
        "https://open-s.info/contacts/"
    ],
    "Неофлекс": [
        "https://yandex.ru/maps/213/moscow/house/Z04YcA5jTEwAQFtvfXtxc39rbQ==/"
    ],
    "Deutsche Bank Technology Center": [
        "https://country.db.com/russia/technology-center/"
    ],
    "IT-компания Иннополис": [
        "http://sezinnopolis.ru/",
        "http://sezinnopolis.ru/kontakty/"
    ],
    "Спринтерра": [
        "https://sprinterra.ru/"
    ],
    "Depo Computers": [
        "https://www.depo.ru/",
        "https://www.depo.ru/contacts/"
    ],
    "ГК «Май»": [
        "https://www.maygk.ru/",
        "https://www.maygk.ru/careers/",
        "https://www.maygk.ru/kontakty/"
    ],
    "Рамакс Интернейшнл": [
        "https://www.ramax.ru/",
        "https://www.ramax.ru/contacts/"
    ],
    "Промышленные инновации Росатом": [
        "https://prominn.ru/",
        "https://prominn.ru/jobs/",
        "https://prominn.ru/contacts/"
    ],
    "Synesis": [
        "http://synesis-group.com/",
        "http://synesis-group.com/#action_form"
    ],
    "Рамэк-вс": [
        "https://www.ramec.ru/",
        "https://www.ramec.ru/#"
    ],
    "Improve group": [
        "http://improve-group.ru/",
        "/job/index.html"
    ],
    "Сканпорт": [
        "https://scanport.ru/",
        "https://scanport.ru/vakansii/"
    ],
    "Adv": [
        "http://adv.ru/"
    ],
    "Гнивц": [
        "https://www.gnivc.ru/",
        "https://career.gnivc.ru",
        "https://www.gnivc.ru/contacts/"
    ],
    "Элар": [
        "https://elar.ru/",
        "https://elar.ru/contacts/"
    ],
    "Maorif Plus": [
        "https://yandex.ru/maps/51/samara/house/YUkYdwRnSEcEQFtpfX14c3pqZA==/"
    ],
    "Группа компаний IT-Center": [
        "https://yandex.ru/maps/org/mybuh_kz/114462401295/"
    ],
    "Инфо-лоджик": [
        "http://info-logic.ru/"
    ],
    "Upsoft Digital": [
        "http://upsoft.uz/",
        "https://upsoft.uz/careers/",
        "https://upsoft.uz/contact/"
    ],
    "Ситек": [
        "https://sitec-it.ru/",
        "https://sitec-it.ru/job/",
        "https://sitec-it.ru/contacts/"
    ],
    "Сибинтек": [
        "http://sibintek.ru/",
        "http://sibintek.ru/company/vacancies/",
        "http://sibintek.ru/company/contacts/"
    ],
    "Открытые Технологии": [
        "http://www.ot.ru/",
        "http://www.ot.ru/career/",
        "http://www.ot.ru/about/head/"
    ],
    "БелИнфоСеть": [
        "https://yandex.ru/maps/org/pedant_ru/116222738958/"
    ],
    "Труконф": [
        "https://trueconf.ru/"
    ],
    "Первый Бит": [
        "https://1solution.ru/"
    ],
    "HFLabs": [
        "http://hflabs.ru/",
        "https://career.hflabs.ru/",
        "http://hflabs.ru/contacts/"
    ],
    "ФГУП Глав Нивц Управления делами Президента Российской Федерации": [
        "http://www.grcc.ru/",
        "http://www.grcc.ru/vacancies",
        "http://www.grcc.ru/contacts"
    ],
    "Бэнкс Софт Системс": [
        "http://bss-s.ru/"
    ],
    "1С-Рарус": [
        "https://www.avtorsoft.ru/",
        "https://www.avtorsoft.ru/company/vacancy/"
    ],
    "Rock Flow Dynamics": [
        "http://rfdyn.ru/",
        "https://rfdyn.ru/vacancies/",
        "https://rfdyn.ru/career/",
        "https://rfdyn.ru/contacts/"
    ],
    "Сплайн-Центр": [
        "https://www.debet.ru/",
        "https://www.debet.ru/spline/contacts/"
    ],
    "Акселот": [
        "https://www.axelot.ru/",
        "https://www.axelot.ru/career/",
        "https://www.axelot.ru/contacts/"
    ],
    "Центр хранения данных": [
        "http://www.rt-dc.ru/",
        "http://www.rt-dc.ru/about/career/",
        "http://www.rt-dc.ru/contacts/"
    ],
    "Custis": [
        "http://www.custis.ru/",
        "https://hh.ru/employer/2537"
    ],
    "1C: Первый Бит": [
        "https://spb.1cbit.ru/",
        "https://spb.1cbit.ru/contacts/"
    ],
    "Группа Компаний Ивбв": [
        "https://ivbvgroup.ru/"
    ],
    "Бэлл Интегратор": [
        "http://www.bellintegrator.ru/"
    ],
    "Национальный Электронно-Информационный Консорциум": [
        "https://neicon.ru/",
        "https://neicon.ru/about/contacts"
    ],
    "Комплит": [
        "https://www.complete.ru/"
    ],
    "Astronis": [
        "http://www.astronis.ru/",
        "http://www.astronis.ru/#kontakty"
    ],
    "Ibm": [
        "http://www.ibm.com/ru-ru"
    ],
    "Sitronics Group": [
        "http://www.sitronics.com/",
        "https://www.sitronics.com/career",
        "https://www.sitronics.com/contact"
    ],
    "Морион": [
        "https://morion.ru/",
        "https://morion.ru/contacts"
    ],
    "Профи Менеджер": [
        "https://yandex.ru/maps/org/sprint_el_regionalny_predstavitel_takskom_v_g_elektrostal/1121447740/"
    ],
    "Омега": [
        "https://omegafuture.ru/",
        "https://spb.hh.ru/search/vacancy?from=employerPage&employer_id=602711",
        "https://omegafuture.ru/contacts/"
    ],
    "ЦОД Компрессор": [
        "https://cloud.croc.ru/technology/data-center",
        "https://cloud.croc.ru/about/contacts/"
    ],
    "Аудатэкс": [
        "http://audatex.ru/",
        "http://audatex.ru/address"
    ],
    "Adicom.kg": [
        "https://yandex.ru/maps/org/adicom_kg/154115118269/"
    ],
    "1С: Первый Бит": [
        "https://www.1cbit.ru/",
        "https://www.1cbit.ru/contacts/"
    ],
    "ЭлигоВижн": [
        "http://www.eligovision.ru/"
    ],
    "Максит": [
        "https://yandex.ru/maps/org/melofon_rf/1710493503/"
    ],
    "РСБХ-Интех": [
        "http://rshb-intech.ru/"
    ],
    "Linx": [
        "https://linx.ru/",
        "https://linx.ru/career",
        "https://linx.ru/contacts"
    ],
    "Хьюлетт Паккард Энтерпрайз": [
        "https://www.hpe.com/ru/ru/"
    ],
    "АйТи Спектр": [
        "http://itspectr.ru/",
        "https://itspectr.ru/vakansii/",
        "https://itspectr.ru/contact/"
    ],
    "Iba Group": [
        "https://ibagroupit.com/"
    ],
    "Naumen": [
        "http://www.naumen.ru/",
        "http://www.naumen.ru/career/vacancies/",
        "http://www.naumen.ru/career/",
        "http://www.naumen.ru/company/contacts/"
    ],
    "ИВК": [
        "https://yandex.ru/maps/org/wepro_ru/48606184449/"
    ],
    "Центр развития перспективных технологий": [
        "http://crpt.ru/",
        "/contact.html"
    ],
    "Иви": [
        "https://www.ivi.ru/",
        "https://corp.ivi.ru/career/#career-vacancy-block"
    ],
    "Медиа Лайн": [
        "https://www.medialine.by/",
        "https://www.medialine.by/about/job/",
        "https://www.medialine.by/contacts/"
    ],
    "ИТ-Сервис": [
        "http://its-samara.com/"
    ],
    "Soft Media Group": [
        "https://softmg.ru/",
        "https://softmg.ru/vakansii/",
        "https://softmg.ru/contacts/"
    ],
    "Osminog Project": [
        "http://www.osminog.biz/",
        "http://www.osminog.biz/company/vacancy/",
        "http://www.osminog.biz/company/contacts/"
    ],
    "Simpl": [
        "https://simpl-group.ru/",
        "https://simpl-group.ru/contacts"
    ],
    "PinscherCRM": [
        "http://pinschercrm.ru/",
        "https://pinschercrm.ru/kontakty/"
    ],
    "Ресурс сервис": [
        "https://yandex.ru/maps/org/pedant_ru/129829202125/"
    ],
    "Синто": [
        "http://sinto.pro/",
        "http://sinto.pro/about/jobs/",
        "http://sinto.pro/about/contacts/"
    ],
    "ЮниСейф": [
        "http://usafe.ru/",
        "http://usafe.ru/contacts/"
    ],
    "Ln Technologies": [
        "http://www.oblaka.tech/",
        "http://www.oblaka.tech/kontakty"
    ],
    "Терн": [
        "http://tern.ru/"
    ],
    "Центр информационно-коммуникационных технологий Республики Башкортостан": [
        "https://www.ciktrb.ru/",
        "about/vacancies/index.html",
        "about/contacts.php.html"
    ],
    "Элвис-Плюс": [
        "http://elvis.ru/",
        "http://elvis.ru/about/kar/",
        "http://elvis.ru/contact/"
    ],
    "Metromax": [
        "https://yandex.ru/maps/org/dom_ru/166830822419/"
    ],
    "Cityads Media": [
        "http://cityads.com/",
        "http://cityads.com/main/about/contacts"
    ],
    "Calltouch": [
        "https://www.calltouch.ru/",
        "https://www.calltouch.ru/about/vacancies/",
        "https://www.calltouch.ru/about/contacts/"
    ],
    "Марвел-Дистрибуция": [
        "https://www.marvel.ru/",
        "https://www.marvel.ru/contacts/"
    ],
    "Лантегра": [
        "http://www.lantegra.ru/",
        "http://www.lantegra.ru/company/vacancy/",
        "http://www.lantegra.ru/contacts/"
    ],
    "Корус Консалтинг СНГ": [
        "https://www.esphere.ru/",
        "https://spb.hh.ru/employer/946607",
        "https://www.esphere.ru/contacts/"
    ],
    "1551": [
        "http://15-51.ru/",
        "http://15-51.ru/career/",
        "http://15-51.ru/kontakty/"
    ],
    "ХайТэк": [
        "http://hi-tech.org/",
        "http://hi-tech.org/about/career"
    ],
    "Исследовательский центр Samsung": [
        "https://yandex.ru/maps/213/moscow/house/Z04YcQJlSkMCQFtvfXt0cXVrYg==/"
    ],
    "Т1 консалтинг": [
        "http://tsconsulting.com/",
        "http://tsconsulting.com/contacts/"
    ],
    "Digital Design": [
        "http://www.digdes.com/",
        "http://www.digdes.com/career/vacancies",
        "http://www.digdes.com/contacts"
    ],
    "Оргтехника Плюс": [
        "https://oplus.ru/",
        "https://oplus.ru/contacts"
    ],
    "Цифровая компания": [
        "http://dcompany.by/"
    ],
    "ITsale": [
        "https://itsale.ru/",
        "https://itsale.ru/contacts/"
    ],
    "Центр информационных технологий": [
        "http://citto.tularegion.ru/",
        "http://citto.tularegion.ru/vakansii/",
        "http://citto.tularegion.ru/kontakty/"
    ],
    "Лист": [
        "http://www.list72.ru/"
    ],
    "Космософт": [
        "https://www.kosmosoft.ru/",
        "https://www.kosmosoft.ru/#contacts"
    ],
    "АйТек": [
        "https://www.aitek.ru/",
        "https://www.aitek.ru/vacancy/",
        "https://www.aitek.ru/contacts/"
    ],
    "1с-ижтиси": [
        "https://xn--1--rlchba2deh.xn--p1ai/",
        "https://izhevsk.hh.ru/search/vacancy?from=employerPage&employer_id=805729&hhtmFrom=employer",
        "https://xn--1--rlchba2deh.xn--p1ai/карьера/привет",
        "https://xn--1--rlchba2deh.xn--p1ai/компания/контакты"
    ],
    "ДатаКрат": [
        "https://www.datakrat.ru/",
        "https://www.datakrat.ru/corporation/contacts"
    ],
    "Байтэкс": [
        "https://bytexgames.ru/"
    ],
    "IT-Сервис": [
        "http://itsportal.ru/"
    ],
    "ДКом": [
        "http://d-kom.net/"
    ],
    "Godel Technologies": [
        "http://careers.godeltech.com/"
    ],
    "iCore": [
        "http://i-core.ru/",
        "http://i-core.ru/ru/vacancies",
        "http://i-core.ru/ru/contacts/"
    ],
    "Сервис Деск": [
        "http://www.service-it.by/"
    ],
    "Atom Bilisim": [
        "http://www.atombilisim.com.tr/"
    ],
    "Системный интегратор Cti": [
        "https://www.cti.ru/",
        "https://www.cti.ru/contacts/"
    ],
    "СейлСервиСолюшенс": [
        "https://www.3c.by/"
    ],
    "Incoma": [
        "https://www.incoma.ru/"
    ],
    "Перфоманс Лаб": [
        "http://www.performance-lab.ru/",
        "http://www.performance-lab.ru/vacancy",
        "http://www.performance-lab.ru/moscow"
    ],
    "МегаКомпСервис": [
        "https://megakomp.ru/services/abonentskoe-obsluzhivanie-kompyuterov-i-serverov",
        "https://megakomp.ru/contacts/"
    ],
    "Синапс": [
        "https://synapsenet.ru/"
    ],
    "Отраслевой центр разработки и внедрения информационных систем": [
        "http://ocrv.ru/",
        "http://ocrv.ru/contacts/"
    ],
    "Нмаркет.ПРО": [
        "https://msk.nmarket.pro/"
    ],
    "Vk Cloud": [
        "https://yandex.ru/maps/20/arhangelsk/house/YEkYcwRmSUQOQFhufXl0eHxqZA==/"
    ],
    "Камин": [
        "https://www.kaminsoft.ru/",
        "/vakancy.html",
        "https://www.kaminsoft.ru/contact"
    ],
    "Ams Software": [
        "https://amssoft.ru/",
        "https://yaroslavl.hh.ru/employer/634253?hhtmFrom=vacancy_search_list",
        "/contacs.php"
    ],
    "Мезекс ИС": [
        "https://themezex.com/?utm_source=yandex_profil"
    ],
    "Гринатом": [
        "https://greenatom.ru/",
        "https://greenatom.ru/vacancy/",
        "https://greenatom.ru/career/",
        "https://greenatom.ru/about_company/contacts/"
    ],
    "ReKassa": [
        "https://rekassa.kz/"
    ],
    "Agora": [
        "https://www.agora.ru/"
    ],
    "Группа Борлас": [
        "https://borlas.ru/",
        "https://borlas.ru/career/vacancies",
        "https://borlas.ru/career",
        "https://borlas.ru/contacts"
    ],
    "Tegrus": [
        "http://www.tegrus.ru/",
        "http://www.tegrus.ru/about/career",
        "http://www.tegrus.ru/contacts"
    ],
    "Максофт": [
        "https://yandex.ru/maps/org/dom_ru/125831280883/"
    ],
    "ФГУП НПП Гамма": [
        "http://www.nppgamma.ru/",
        "http://www.nppgamma.ru/about/otdel_prodazh/"
    ],
    "Skyeer": [
        "https://skyeermap.com/",
        "https://skyeermap.com/#contacts"
    ],
    "Bel Huawei Technologies": [
        "https://www.huawei.com/",
        "https://career.huawei.com/"
    ],
    "Платформа Офд": [
        "https://platformaofd.ru/",
        "https://platformaofd.ru/contacts/"
    ],
    "Импульс Телеком": [
        "https://yandex.ru/maps/org/zheleza_net/1614231176/"
    ],
    "Перемена": [
        "https://peremena.com/",
        "https://peremena.com/about/vacancy/",
        "https://peremena.com/contacts/"
    ],
    "Surf": [
        "https://surf.ru/",
        "https://surf.ru/career/",
        "https://surf.ru/contacts/"
    ],
    "Астра": [
        "https://astralinux.ru/",
        "https://astralinux.ru/about/career/vacancies/",
        "https://astralinux.ru/about/career/",
        "https://astralinux.ru/about/company/#menu__contacts"
    ],
    "Финтех": [
        "https://yandex.ru/maps/org/r_lab/99761130230/"
    ],
    "Корус Консалтинг": [
        "https://korusconsulting.ru/",
        "https://spb.hh.ru/employer/675",
        "https://korusconsulting.ru/contacts/"
    ],
    "Акционерное общество Информатика": [
        "https://informatika37.ru/",
        "https://informatika37.ru/vakansii/",
        "https://informatika37.ru/kontakty/"
    ],
    "E-legion": [
        "https://www.e-legion.ru/",
        "https://www.e-legion.ru/contacts/"
    ],
    "Дататех": [
        "https://yandex.ru/maps/213/moscow/house/Z04YcAJiQUcFQFtvfXtxeX9jZw==/"
    ],
    "Epam": [
        "https://careers.epam.by/"
    ],
    "Отр 2000": [
        "http://otr.ru/",
        "http://otr.ru/contacts/"
    ],
    "Бифит": [
        "http://legal-bifit.ru/",
        "http://legal-bifit.ru/about#contacts"
    ],
    "Оберон": [
        "http://www.oberon-it.ru/"
    ],
    "Сбербанк-АСТ": [
        "http://www.sberbank-ast.ru/"
    ],
    "Випакс+": [
        "https://vipaks.com/",
        "https://vipaks.com/contacts/"
    ],
    "Очень Интересно": [
        "http://interesnee.ru/"
    ],
    "Дивит Про": [
        "https://yandex.ru/maps/org/r_lab/99761130230/"
    ],
    "SoftTeco": [
        "https://softteco.team/",
        "https://softteco.team/vacancies/"
    ],
    "ООО Инлайн технолоджис": [
        "http://www.in-line.ru/",
        "http://www.in-line.ru/career/",
        "http://www.in-line.ru/about/contacts/"
    ],
    "Сонет": [
        "https://yandex.ru/maps/org/dom_ru_biznes/72898495935/"
    ],
    "Код Безопасности": [
        "https://www.securitycode.ru/",
        "https://www.securitycode.ru/company/contacts/"
    ],
    "ПИК-Аренда": [
        "https://pik-arenda.ru/",
        "https://pik-arenda.ru/contacts/"
    ],
    "Ипол": [
        "http://ipol.ru/",
        "http://ipol.ru/contacts/"
    ],
    "Mwi": [
        "https://mwi.me/",
        "https://mwi.me/contacts/"
    ],
    "Icore": [
        "https://yandex.ru/maps/org/mybuh_kz/114462401295/"
    ],
    "EffectiveSoft": [
        "http://www.effectivesoft.com/"
    ],
    "IT Webstyle": [
        "https://webstyle.top/",
        "https://webstyle.top/vakansii",
        "https://webstyle.top/kontakty"
    ],
    "АйТи Групп": [
        "https://yandex.ru/maps/org/dom_ru_biznes/149414182811/"
    ],
    "Orbl": [
        "https://orbl.ru/"
    ],
    "edna": [
        "https://edna.ru/",
        "https://edna.ru/career/",
        "https://edna.ru/contacts/"
    ],
    "Хьюмен Систем": [
        "https://www.hs.by/",
        "https://www.hs.by/company/vacancy/",
        "https://www.hs.by/contacts/"
    ],
    "ФГБУ Российский фонд информации по природным ресурсам и охране окружающей среды Минприроды России": [
        "https://rfi.mnr.gov.ru/",
        "https://rfi.mnr.gov.ru/about/vacancies/",
        "https://rfi.mnr.gov.ru/contacts/"
    ],
    "Системный интегратор Итерра": [
        "https://yandex.ru/maps/org/dom_ru/166830822419/"
    ],
    "АйТиДом": [
        "https://www.itdom-nn.ru/",
        "/karera.html",
        "/kontakty.html"
    ],
    "Тринити": [
        "https://www.trinitygroup.ru/",
        "https://www.trinitygroup.ru/about/vacansy/",
        "https://www.trinitygroup.ru/about/address/"
    ],
    "Крибрум": [
        "https://www.kribrum.ru/",
        "https://www.kribrum.ru/contacts/"
    ],
    "Интегро": [
        "http://integro44.ru/"
    ],
    "Северная Корона": [
        "https://yandex.ru/maps/org/pedant_ru/69226387986/"
    ],
    "ККС": [
        "https://ccrs.ru/",
        "https://ccrs.ru/contacts/"
    ],
    "ДиСиЛоджик": [
        "https://dclogic.ru/",
        "https://dclogic.ru/contacts/"
    ],
    "ИЦ Телеком-сервис": [
        "https://www.teleserv.ru/"
    ],
    "Dassault Systemes": [
        "http://www.3ds.com/russia"
    ],
    "Abcp": [
        "https://www.abcp.ru/",
        "https://abcp.ru/contacts"
    ],
    "Allcorrect Group": [
        "https://www.allcorrectgames.ru/"
    ],
    "Умные решения": [
        "https://umsol.ru/",
        "https://umsol.ru/contacts/"
    ],
    "Институт информационных технологий": [
        "http://www.ins-iit.ru/",
        "/index.php/home/kontakty-2"
    ],
    "Центр Компьютеризации": [
        "https://yandex.ru/maps/192/vladimir/house/YEkYdQJmQEUDQFtsfX1zd35jZw==/"
    ],
    "Vrp Consulting": [
        "https://yandex.ru/maps/221/chimkent/house/YkAYcwBkQU0AQFpofX9wcHllYw==/"
    ],
    "АйТи-Релакс": [
        "https://yandex.ru/maps/org/pedant_ru/142301023129/"
    ],
    "А-Системс": [
        "http://www.a-systems.ru.com/",
        "http://www.a-systems.ru.com/node/114"
    ],
    "Auxo": [
        "https://auxo-it.ru/"
    ],
    "Эксат-бел": [
        "https://zpos.by/",
        "https://zpos.by/contacts"
    ],
    "Трайтек Инфосистемс": [
        "https://yandex.ru/maps/org/pedant_ru/81916901599/"
    ],
    "Юпитер": [
        "http://upiter.su/",
        "http://upiter.su/company/vacancy/",
        "http://upiter.su/contacts/"
    ],
    "Форс": [
        "http://www.fors.ru/",
        "http://www.fors.ru/career/",
        "http://www.fors.ru/about-company/contacts/"
    ],
    "Лвком Проект": [
        "https://lwcom.ru/",
        "https://lwcom.ru/job/",
        "https://lwcom.ru/about/contacts/"
    ],
    "Ngenix": [
        "https://ngenix.net/",
        "https://ngenix.net/career/",
        "https://ngenix.net/contacts/"
    ],
    "Бевалекс": [
        "http://www.bevalex.by/"
    ],
    "NexTouch": [
        "https://nextouch.ru/"
    ],
    "Jivo": [
        "https://www.jivo.ru/",
        "https://www.jivo.ru/vacancy",
        "https://www.jivo.ru/contacts"
    ],
    "Навигационные решения": [
        "https://nvgn.ru/",
        "https://nvgn.ru/contacts/"
    ],
    "САМО-Софт": [
        "https://samo.ru/",
        "/about/vacancy.html",
        "/about/contacts.html"
    ],
    "Росо ГРУП": [
        "https://www.rosogroup.ru/"
    ],
    "Plazius": [
        "http://plazius.ru/"
    ],
    "Белорусский межбанковский расчетный центр": [
        "http://www.bisc.by/",
        "http://www.bisc.by/o-kompanii/vakansii"
    ],
    "Крипто-Про": [
        "http://www.cryptopro.ru/",
        "http://www.cryptopro.ru/job",
        "http://www.cryptopro.ru/contacts"
    ],
    "Лаборатория Наносемантика": [
        "https://nanosemantics.ai/",
        "https://nanosemantics.ai/career",
        "https://nanosemantics.ai/contacts"
    ],
    "Кортис": [
        "http://www.kortis.msk.ru/",
        "http://www.kortis.msk.ru/contacts/"
    ],
    "Сервис-Центр Артсервис": [
        "https://yandex.ru/maps/org/pedant_ru/124990073597/"
    ],
    "Артвелл": [
        "http://www.artwell.ru/",
        "http://www.artwell.ru/about/job/",
        "http://www.artwell.ru/contacts/"
    ],
    "PlanX": [
        "http://planx.one/"
    ],
    "Техартгруп": [
        "https://www.itechart.by/"
    ],
    "Рндсофт": [
        "http://rnd-soft.ru/",
        "http://rnd-soft.ru/job?category=all"
    ],
    "Discus: разработка и создание электронных курсов Сдо": [
        "https://ediscus.ru/"
    ],
    "Гарант-Мордовия": [
        "http://grnt.ru/",
        "https://grnt.ru/about/vakansii/",
        "https://grnt.ru/contacts/"
    ],
    "Карма Групп": [
        "https://www.karma-group.ru/",
        "https://www.karma-group.ru/about/vacancies/",
        "https://www.karma-group.ru/about/contacts/"
    ],
    "HP Inc": [
        "http://www.hp.ru/"
    ],
    "Крикунов и Партнеры Бизнес Системы": [
        "http://www.kpbs.ru/",
        "http://www.kpbs.ru/vakansii/",
        "http://www.kpbs.ru/kontakty/"
    ],
    "Интеллект Технологии": [
        "http://xn----ftbeabofaniaeshpb1dfb5d.xn--p1ai/"
    ],
    "Доспринт": [
        "https://dosprint.ru/",
        "https://dosprint.ru/contacts/"
    ],
    "Легион Бизнес Систем": [
        "https://legion.ru/",
        "https://legion.ru/#contacts"
    ],
    "Kns Neva": [
        "https://yandex.ru/maps/org/m_video/1127549053/"
    ],
    "Софт Навигатор": [
        "http://www.softnavi.ru/"
    ],
    "Про-М": [
        "https://yandex.ru/maps/org/pedant_ru/142301023129/"
    ],
    "Serverconf. uz": [
        "http://serverconf.uz/"
    ],
    "Обит": [
        "https://yandex.ru/maps/org/dom_ru/117838876646/"
    ],
    "Konnekt Service Center": [
        "http://konnekt.kz/",
        "http://remontphone.konnekt.kz/?page_id=124"
    ],
    "Umbrella IT": [
        "https://umbrellait.ru/",
        "https://umbrellait.ru/careers/",
        "https://umbrellait.ru/contacts/"
    ],
    "Alsi": [
        "http://alsi.kz/"
    ],
    "Газпром Информ": [
        "http://inform.gazprom.ru/",
        "https://www.gazpromvacancy.ru/",
        "http://inform.gazprom.ru/career/"
    ],
    "Cns": [
        "https://cns-corp.ru/",
        "https://cns-corp.ru/contacts/"
    ],
    "Прострим": [
        "https://pro-stream.ru/?utm_source=maps",
        "https://pro-stream.ru/vacancies",
        "https://pro-stream.ru/contacts"
    ],
    "ГК Системный администратор": [
        "https://admin-samara.ru/",
        "https://admin-samara.ru/#contact"
    ],
    "Интеллектуальные системы Само Систем": [
        "https://yandex.ru/maps/org/m_video/1859949379/"
    ],
    "Сиблион": [
        "https://www.siblion.ru/",
        "https://www.siblion.ru/contacts"
    ],
    "Datahouse.ru": [
        "https://datahouse.ru/"
    ],
    "РосАвтоматизация": [
        "https://ra38.ru/",
        "https://ra38.ru/kontakt/"
    ],
    "Axenix": [
        "http://axenix.pro/",
        "https://axenix.pro/career"
    ],
    "Главбух": [
        "https://www.gbsoft.by/",
        "https://www.gbsoft.by/contacts/"
    ],
    "ИТ-Артис": [
        "http://www.it-artis.ru/"
    ],
    "ТЭК Информ": [
        "http://tek-inform.ru/",
        "http://tek-inform.ru/company/vacancy/",
        "http://tek-inform.ru/contacts/"
    ],
    "Аллока": [
        "http://www.alloka.ru/",
        "https://alloka.ru/about#vacancy",
        "https://alloka.ru/about#contacts"
    ],
    "Quarta": [
        "http://www.quarta.su/"
    ],
    "АО Ринет": [
        "http://www.sibnet.ru/",
        "https://www.sibnet.ru/vacancy/"
    ],
    "Легион Проект": [
        "https://www.legion-colour.ru/",
        "https://www.legion-colour.ru/contacts/"
    ],
    "Брэндстудио": [
        "https://bstd.ru/"
    ],
    "Элси": [
        "https://www.elsy.ru/"
    ],
    "Центр обработки данных телевизионного технического центра Останкино": [
        "http://dc.ostankino.ru/"
    ],
    "Прогресс": [
        "https://magnetron.su/"
    ],
    "Ангара Технолоджиз ГРУП": [
        "https://www.angarasecurity.ru/",
        "https://www.angarasecurity.ru/job/",
        "https://www.angarasecurity.ru/contacts/"
    ],
    "Корада Консалтинг": [
        "https://corada.ru/",
        "https://team.corada.ru/"
    ],
    "Арена ИТ": [
        "https://yandex.ru/maps/org/pedant_ru/177205311717/"
    ],
    "Инфотех ГРУП": [
        "https://infotech.group/",
        "https://infotech.group/ru/developers",
        "https://infotech.group/ru/contacts"
    ],
    "At Consulting": [
        "https://www.at-consulting.ru/",
        "https://www.at-consulting.ru/about_company/contacts/"
    ],
    "Аксис": [
        "https://axsysmarket.ru/",
        "https://axsysmarket.ru/contacts"
    ],
    "Бюджетные и Финансовые Технологии": [
        "http://www.bftcom.com/",
        "http://www.bftcom.com/career/",
        "http://www.bftcom.com/company/contacts/"
    ],
    "Ритейл Сервис 24": [
        "https://rts24.com/",
        "https://rts24.com/about/contacts/"
    ],
    "ТКС": [
        "https://wow2print.com/"
    ],
    "Цифровые технологии": [
        "http://www.dtvladimir.ru/"
    ],
    "Технократ": [
        "https://www.tkrat.ru/",
        "https://www.tkrat.ru/contact/"
    ],
    "Инфорсер Инжиниринг": [
        "https://yandex.ru/maps/213/moscow/house/Z04YcAZhT0IHQFtvfXtxdHpkZQ==/"
    ],
    "Nitec": [
        "https://www.nitec.kz/"
    ],
    "Ай-Джи-Эй Технологии": [
        "http://www.igatec.com/",
        "https://igatec.com/career/"
    ],
    "Topcase": [
        "https://www.topcase.ru/"
    ],
    "Квартплата 24": [
        "https://www.gosuslugi.ru/10373/1"
    ],
    "Компания Аксус Компьютеры": [
        "https://yandex.ru/maps/org/m_video/1068449614/"
    ],
    "Softline": [
        "https://softline.ru/",
        "https://softline.ru/job",
        "https://softline.ru/about/contact"
    ],
    "Группа компаний ЦРТ": [
        "https://www.speechpro.ru/",
        "https://www.speechpro.ru/career",
        "https://www.speechpro.ru/contacts"
    ],
    "ФГУП Главный радиочастотный центр": [
        "http://www.grfc.ru/",
        "http://www.grfc.ru/grfc/about/vacancy/",
        "http://www.grfc.ru/grfc/contacts/"
    ],
    "B2B-Center": [
        "https://www.b2b-center.ru/"
    ],
    "Рамэк-ВС": [
        "https://www.ramec.ru/",
        "https://www.ramec.ru/#"
    ],
    "Национальная компьютерная корпорация": [
        "https://ncc.ru/",
        "https://ncc.ru/contacts"
    ],
    "Арбайт": [
        "https://www.arbyte.ru/",
        "https://arbyte.ru/contact/"
    ],
    "Интерсофт": [
        "http://www.inter-soft.ru/",
        "http://www.inter-soft.ru/kontaky/"
    ],
    "Стилсофт": [
        "https://stilsoft.ru/",
        "https://stilsoft.ru/vacancies",
        "https://stilsoft.ru/page/contacts"
    ],
    "Эникей": [
        "https://yandex.ru/maps/org/pedant_ru/75654446908/"
    ],
    "ЭйВиДи-систем": [
        "https://open4u.ru/"
    ],
    "АС": [
        "http://www.asntl.ru/",
        "https://www.asntl.ru/contact/"
    ],
    "Центр разработки для обнаружения ошибок": [
        "http://crdoo.ru/",
        "http://crdoo.ru/#contacts"
    ],
    "РГ-Софт": [
        "https://www.rg-soft.ru/"
    ],
    "Варум": [
        "https://warum.ru/",
        "https://warum.ru/about-us/#sppb-addon-1638441574991"
    ],
    "Пмсофт": [
        "https://www.pmsoft.ru/"
    ],
    "Buta Grup": [
        "https://www.butagrup.com.tr/"
    ],
    "Улей": [
        "https://www.wehive.ru/",
        "https://www.wehive.ru/contacts/"
    ],
    "АСТ": [
        "http://www.acti.ru/",
        "http://www.acti.ru/kontakty"
    ],
    "Кластер": [
        "https://klaster24.ru/"
    ],
    "Casper Genel Müdürlük": [
        "http://www.casper.com.tr/"
    ],
    "Сайтсофт": [
        "https://www.sitesoft.ru/"
    ],
    "Си Проект": [
        "https://seaproject.ru/",
        "https://seaproject.ru/career",
        "https://seaproject.ru/contacts"
    ],
    "Мегабайт Сервис": [
        "http://www.mbkazan.ru/"
    ],
    "KocSistem Head Office": [
        "http://www.kocsistem.com.tr/"
    ],
    "TripAggregator": [
        "https://yandex.ru/maps/org/resursny_tsentr_ruki/1031453324/"
    ],
    "АвангардСофт": [
        "http://www.avangardsoft.ru/"
    ],
    "Decart it-production": [
        "https://dcrt.it/",
        "https://dcrt.it/vacancies/"
    ],
    "Intensa": [
        "https://yandex.ru/maps/213/moscow/house/Z04YcwdkT00GQFtvfXRxd3lgZA==/"
    ],
    "Направление ру": [
        "https://www.napravlenie.ru/",
        "https://www.napravlenie.ru/contacts"
    ],
    "Кит": [
        "https://kit23.ru/",
        "https://kit23.ru/company/vacancy/",
        "https://kit23.ru/contacts/"
    ],
    "КомпрайЭкспресс сервисный центр": [
        "https://comprayexpress.ru/"
    ],
    "Информатика": [
        "https://yandex.ru/maps/org/pedant_ru/86872860936/"
    ],
    "Т1 Cloud": [
        "https://t1-cloud.ru/",
        "https://t1-cloud.ru/contacts/"
    ],
    "Ант-Хилл": [
        "http://1c-ant.ru/",
        "http://1c-ant.ru/contacts/"
    ],
    "Стэл КС": [
        "http://www.stel.ru/",
        "http://www.stel.ru/kontakty/"
    ],
    "Южная Софтверная Компания": [
        "http://www.usk.ru/",
        "http://www.usk.ru/company/vacancy/",
        "http://www.usk.ru/contacts/"
    ],
    "Техномаркет": [
        "http://www.tm-v.ru/",
        "https://tm-v.ru/o-kompanii/kontaktyi/"
    ],
    "3data": [
        "https://3data.ru/",
        "https://3data.ru/about/vacancy",
        "https://3data.ru/contacts"
    ],
    "Конфиг ИТ": [
        "https://configit.ru/",
        "https://configit.ru/kontakty/"
    ],
    "1С-Автоматизация": [
        "https://www.avtomatizator.ru/",
        "https://www.avtomatizator.ru/company/vacancy/"
    ],
    "Ласнет": [
        "http://www.lasnet.pro/",
        "contacts.html"
    ],
    "Сван": [
        "http://swan-it.ru/",
        "http://swan-it.ru/company/career/"
    ],
    "Копикон": [
        "https://yandex.ru/maps/org/pedant_ru/1877591715/"
    ],
    "Ofd.ru": [
        "https://ofd.ru/"
    ],
    "Поинт": [
        "https://www.pointcad.ru/"
    ],
    "СолЭнерго": [
        "https://solenergo.net/",
        "https://solenergo.net/kontakty"
    ],
    "НТП Унисервис - инженерный центр Sauter": [
        "http://www.uniservice.ru/"
    ],
    "ITKey": [
        "https://itkey.com/",
        "https://itkey.tech",
        "https://itkey.com/#contacts"
    ],
    "Нетрика": [
        "http://netrika.ru/",
        "http://job.netrika.ru/",
        "https://netrika.ru/contacts"
    ],
    "Асбк": [
        "https://yandex.ru/maps/org/dom_ru/1239132428/"
    ],
    "LightNet Complex": [
        "https://yandex.ru/maps/org/r_lab/99761130230/"
    ],
    "Автотека": [
        "https://autoteka.ru/"
    ],
    "IT-Аутсорсинг Компания Скай": [
        "https://sky-rzn.ru/"
    ],
    "Хэдвэй Компани": [
        "https://www.hwcompany.ru/"
    ],
    "РИВЦ-Пулково": [
        "https://rivc-pulkovo.ru/",
        "https://rivc-pulkovo.ru/career/",
        "https://rivc-pulkovo.ru/contacts/"
    ],
    "Плаут Консалтинг": [
        "http://www.plaut.com/ru",
        "http://www.plaut.com/ru/career",
        "http://www.plaut.com/ru/contacts"
    ],
    "БелТрансСпутник": [
        "https://beltranssat.by/resheniya/kontrol-topliva.html",
        "https://beltranssat.by/vakansii.html",
        "https://beltranssat.by/kontakty.html"
    ],
    "Креативная группа Феникс": [
        "https://phoenix-cg.ru/"
    ],
    "Решение-Н": [
        "http://www.reshenie-n.ru/"
    ],
    "Бизнес-Азимут": [
        "https://bazt.ru/",
        "https://bazt.ru/vacancy/",
        "https://bazt.ru/contact/"
    ],
    "ПолисСофт": [
        "http://www.policesoft.ru/"
    ],
    "Mobile Inform Group": [
        "http://m-infogroup.ru/",
        "https://m-infogroup.ru/o-kompanii/kontakty/"
    ],
    "Решение": [
        "https://re96.ru/",
        "https://re96.ru/company/vacancy/",
        "https://re96.ru/contacts/"
    ],
    "Ланит-поволжье": [
        "http://www.lanitnn.ru/",
        "vakansii.html",
        "kontaktyi.html"
    ],
    "О-Портал": [
        "http://oportal.biz/",
        "/index.php/contact"
    ],
    "ItYota": [
        "https://yandex.ru/maps/org/nakhabino_ru/1751829840/"
    ],
    "НБ Сервис": [
        "http://nb-serv.com/",
        "https://nb-serv.com/job/"
    ],
    "Е-офд": [
        "https://e-ofd.ru/",
        "https://e-ofd.ru/#contacts-section"
    ],
    "1C Первый Бит": [
        "https://sochi.1cbit.ru/",
        "https://sochi.1cbit.ru/contacts/"
    ],
    "Кью-центр": [
        "http://www.q.center/",
        "https://q.center/kontakty-2/"
    ],
    "1С: Франчайзи БЦ Профит": [
        "https://www.bcprofit.ru/",
        "https://www.bcprofit.ru/1с_зеленоград/"
    ],
    "МВП Свемел": [
        "http://www.swemel.ru/"
    ],
    "Клиентская база": [
        "https://clientbase.ru/",
        "https://clientbase.ru/contacts/"
    ],
    "Глобал-Софт": [
        "https://www.globals.ru/",
        "https://www.globals.ru/about/vacancies/"
    ],
    "Банковские информационные системы": [
        "http://www.bis.ru/"
    ],
    "Itps": [
        "http://itps.com/",
        "http://itps.com/company/vacancies",
        "http://itps.com/contacts"
    ],
    "Содействие, склад": [
        "https://yandex.ru/maps/org/pedant_ru/14925118178/"
    ],
    "ГК Решение": [
        "http://gkreshenie.ru/",
        "https://gkreshenie.ru/vakansii/",
        "https://gkreshenie.ru/kontakty/"
    ],
    "Антор Бизнес Решения": [
        "https://www.antor.ru/"
    ],
    "Сфера": [
        "http://www.sphaera.ru/",
        "https://sphaera.ru/career",
        "https://sphaera.ru/contacts"
    ],
    "Algorithm Computers": [
        "http://a-computers.ru/",
        "http://a-computers.ru/contact"
    ],
    "Московская городская служба сервиса": [
        "https://yandex.ru/maps/org/r_lab/99761130230/"
    ],
    "АБН-Хайтек": [
        "https://www.abn.ru/",
        "https://www.abn.ru/articles/1695-shema_proezda_v_ofis_kompanii_abn/"
    ],
    "Active +": [
        "https://www.acomps.ru/",
        "/company/kontakty.php"
    ],
    "Смарт прайс": [
        "https://www.smartpricing.ru/",
        "https://www.smartpricing.ru/visit_us"
    ],
    "Софком": [
        "http://www.sofcom.ru/"
    ],
    "Maxis": [
        "https://maxis-it.ru/",
        "https://maxis-it.ru/contacts/"
    ],
    "АдатаСофтваре РД": [
        "https://adata.by/"
    ],
    "Арбис": [
        "https://arbis29.ru/",
        "https://arbis29.ru/contacts/"
    ],
    "ИТ интегратор Врса": [
        "http://xn--90agcqfex5h.xn--p1ai/"
    ],
    "Paladin": [
        "https://www.paladin-group.ru/",
        "https://www.paladin-group.ru/company/career/",
        "https://www.paladin-group.ru/contacts/"
    ],
    "Мастерская Тардис": [
        "https://yandex.ru/maps/org/pedant_ru/144850602031/"
    ],
    "Мир электроники и техники": [
        "https://mireit.ru/"
    ],
    "Харун Пехливанның Ақпараттық Технологиялар Тобы": [
        "https://www.rehber.com.tr/harunpehlivan"
    ],
    "Айкэн": [
        "https://yandex.ru/maps/org/r_lab/99761130230/"
    ],
    "I-Digital": [
        "https://i-dgtl.ru/",
        "https://i-dgtl.ru/kontakty/"
    ],
    "РСК Технологии": [
        "http://rscgroup.ru/",
        "http://rscgroup.ru/vacancies/",
        "http://rscgroup.ru/contacts/"
    ],
    "Солар": [
        "https://rt-solar.ru/"
    ],
    "Аскрин": [
        "http://www.ascreen.ru/"
    ],
    "Информационно-технический центр": [
        "https://yandex.ru/maps/org/a_v_k/1070080831/"
    ],
    "Элпо плюс": [
        "https://elpo.ru/",
        "https://elpo.ru/#block832"
    ],
    "Veeam Software": [
        "https://careers.veeam.com/"
    ],
    "АйТиЛенд": [
        "https://www.itland.ru/",
        "https://www.itland.ru/about/kontakty-i-obratnaya-svyaz/"
    ],
    "Сотел": [
        "https://sotel.su/",
        "https://sotel.su/about/contacts/"
    ],
    "Itsoft дата-центр Nord-4 Tier III": [
        "https://itsoft.ru/data-center/dedicated",
        "https://itsoft.ru/jobs/",
        "https://itsoft.ru/feedback/"
    ],
    "Газпром информ": [
        "http://inform.gazprom.ru/",
        "https://www.gazpromvacancy.ru/",
        "http://inform.gazprom.ru/career/"
    ],
    "Опен Вижн": [
        "https://www.open-vision.ru/",
        "https://www.open-vision.ru/about/career/"
    ],
    "Информационные системы и стратегии": [
        "http://infsys.ru/",
        "aboutus/companycontact.html"
    ],
    "Инсофт": [
        "https://yandex.ru/maps/org/pedant_ru/243491332633/"
    ],
    "Supl. biz": [
        "https://supl.biz/",
        "https://supl.biz/job/"
    ],
    "A&A": [
        "http://www.a2company.ru/"
    ],
    "Фактор роста": [
        "http://growfactor.ru/",
        "contacts.html"
    ],
    "Hands App": [
        "http://handsapp.ru/",
        "http://handsapp.ru/vakansii",
        "http://handsapp.ru/contacts"
    ],
    "Окдеск": [
        "https://okdesk.ru/"
    ],
    "Epg Service": [
        "http://epgservice.ru/",
        "http://epgservice.ru/company/jobs/",
        "http://epgservice.ru/contacts/"
    ],
    "TrustSol": [
        "https://www.trustsol.ru/",
        "https://www.trustsol.ru/about/vacancy/",
        "https://www.trustsol.ru/contacts/"
    ],
    "Статус Комплайнс": [
        "http://www.status-it.com/"
    ],
    "DataMobile": [
        "http://data-mobile.ru/",
        "https://scanport.ru/vakansii/",
        "https://scanport.ru/kontakty/"
    ],
    "Hrscanner": [
        "https://hrscanner.ru/"
    ],
    "АВ Софт": [
        "https://avsw.ru/",
        "https://avsw.ru/about/vacancies",
        "https://avsw.ru/about/contacts"
    ],
    "Vlad IT": [
        "https://vladit.ru/",
        "https://vladit.ru/vacancies/",
        "https://vladit.ru/contacts/"
    ],
    "Dr. Web": [
        "http://company.drweb.com/"
    ],
    "Konica Minolta": [
        "http://www.konicaminolta.ru/",
        "http://www.konicaminolta.ru/ru-ru/contacts"
    ],
    "Эксклюзивные бизнес-технологии": [
        "https://excbt.ru/",
        "https://excbt.ru/#b2151"
    ],
    "Новые медиа": [
        "https://ru.riki.team/work/licensing/",
        "https://ru.riki.team/about/vacancies/",
        "https://ru.riki.team/contacts/"
    ],
    "Уральские кабельные сети - Озёрск": [
        "http://www.ozersk.net/"
    ],
    "Pro IT": [
        "http://proitr.ru/"
    ],
    "Дакор": [
        "https://yandex.ru/maps/org/dom_ru_biznes/95820076828/"
    ],
    "Майнинг отель Pimnara": [
        "https://yandex.ru/maps/org/wepro_ru/48606184449/"
    ],
    "Азимут Телеком": [
        "http://aztl.ru/"
    ],
    "СлавПрог": [
        "http://slavsoft.ru/",
        "contacts.html"
    ],
    "РусКом": [
        "https://rk1.ru/",
        "https://rk1.ru/contacts/"
    ],
    "ИТ-Завод": [
        "https://www.itzavod.ru/",
        "https://www.itzavod.ru/company/career/",
        "https://www.itzavod.ru/company/contacts/"
    ],
    "ГазИнтех": [
        "https://yandex.ru/maps/org/r_lab/99761130230/"
    ],
    "Альвента": [
        "https://alveco.ru/",
        "/contacts.htm"
    ],
    "Ist": [
        "https://yandex.ru/maps/org/dom_ru/166830822419/"
    ],
    "Компьютерный дом Нэф": [
        "http://www.nef.ru/",
        "http://www.nef.ru/contact"
    ],
    "Альфаком": [
        "http://alfakom.org/"
    ],
    "Ролис": [
        "http://www.rlisystems.ru/",
        "http://www.rlisystems.ru/vac/",
        "http://www.rlisystems.ru/contacts/"
    ],
    "Индивидуальные информационные системы": [
        "https://indins.ru/",
        "https://indins.ru/vacancy",
        "https://indins.ru/contacts"
    ],
    "Центр технических решений Грифон": [
        "https://yandex.ru/maps/org/apple_re_cover/1787222599/"
    ],
    "WSS-Consulting": [
        "https://wss-consulting.ru/",
        "https://wss-consulting.ru/about/jobs/",
        "https://wss-consulting.ru/contacts/"
    ],
    "At-it.ru": [
        "https://at-it.ru/",
        "https://at-it.ru/kontakty/"
    ],
    "Портал-Юг": [
        "http://www.portal-yug.ru/",
        "http://www.portal-yug.ru/vacancies/",
        "http://www.portal-yug.ru/career/",
        "http://www.portal-yug.ru/contacts/"
    ],
    "Başakşehir Living Lab": [
        "http://basaksehir-livinglab.com/"
    ],
    "Loginom Company": [
        "https://loginom.ru/",
        "https://loginom.ru/company/contacts"
    ],
    "Донтеко": [
        "http://donteco.com/"
    ],
    "Медицинский информационно-аналитический центр": [
        "http://miac.nnov.ru/",
        "http://miac.nnov.ru/vakansii/",
        "http://miac.nnov.ru/kontakty",
        "http://miac.nnov.ru/kontakty/"
    ],
    "Росси": [
        "https://rossi.ru/",
        "https://rossi.ru/jobs/",
        "https://rossi.ru/contacts/"
    ],
    "Милдсофт": [
        "https://www.startexam.ru/",
        "https://www.startexam.ru/contacts"
    ],
    "Айтоника": [
        "http://itonica.ru/",
        "http://itonica.ru/contacts/"
    ],
    "Центр информационных технологий Мингорисполкома": [
        "http://it-minsk.by/",
        "http://it-minsk.by/kontakty"
    ],
    "Сис Телеком": [
        "https://sistele.com/",
        "https://sistele.com/contacts/"
    ],
    "Роксис": [
        "https://www.roksis.ru/",
        "https://www.roksis.ru/vacancies/",
        "https://www.roksis.ru/contacts/"
    ],
    "ИТТС": [
        "http://www.ittsystems.ru/"
    ],
    "Фьюжн ИТ-интегратор": [
        "https://efusion.ru/",
        "https://efusion.ru/about/career/",
        "https://efusion.ru/contacts/"
    ],
    "Двдм.ру": [
        "https://yandex.ru/maps/org/ukazka_ru/1011224307/"
    ],
    "34web": [
        "https://34web.ru/",
        "https://34web.ru/company/vacancy/"
    ]
}